safe_transformer-0.0.5.dist-info/RECORD
safe_transformer-0.0.5.dist-info/METADATA
safe_transformer-0.0.5.dist-info/metadata.json
safe_transformer-0.0.5.dist-info/top_level.txt
safe_transformer-0.0.5.dist-info/WHEEL
safe_transformer-0.0.5.dist-info/DESCRIPTION.rst
SafeTransformer/SafeTransformer.py
SafeTransformer/__init__.py
safe-transformer/SafeTransformer.py
safe-transformer/__init__.py
