Metadata-Version: 2.0
Name: safe-transformer
Version: 0.0.5
Summary: Build explainable ML models using surrogate models.
Home-page: https://github.com/olagacek/SAFE
Author: Aleksandra Gacek, Piotr Luboń
Author-email: lubonp@student.mini.pw.edu.pl, gaceka@student.mini.pw.edu.pl
License: UNKNOWN
Platform: UNKNOWN
Classifier: Programming Language :: Python :: 3
Classifier: License :: OSI Approved :: MIT License
Classifier: Operating System :: OS Independent
Requires-Dist: numpy
Requires-Dist: ruptures
Requires-Dist: sklearn
Requires-Dist: pandas
Requires-Dist: scipy
Requires-Dist: kneed
